rgpy-0.2.4.dist-info/METADATA
rgpy-0.2.4.dist-info/WHEEL
rgpy-0.2.4.dist-info/licenses/LICENSE
rgpy/__init__.py
rgpy/rgpy.cpython-312-darwin.so
rgpy-0.2.4.dist-info/RECORD
