Metadata-Version: 2.4
Name: rgpy
Version: 0.2.4
Requires-Dist: twine>=6.1.0
License-File: LICENSE
Summary: Rust-powered blazing-fast regex search for Python
Author-email: Junwon Lee <cpprhtn@naver.com>
License: MIT
Requires-Python: >=3.12
